[
 {
     "id": 1,
     "title": "суши1",
     "itemsInBox": 6,
     "weight": 180,
     "price": 100,
     "imgSrc": "california-hit.jpg"
 },
  {
     "id": 2,
     "title": "суши2",
     "itemsInBox": 6,
     "weight": 280,
     "price": 150,
     "imgSrc": "zapech-california.jpg"
 },
  {
     "id": 3,
     "title": "суши3",
     "itemsInBox": 6,
     "weight": 100,
     "price": 120,
     "imgSrc": "philadelphia.jpg"
 },
  {
     "id": 4,
     "title": "суши4",
     "itemsInBox": 6,
     "weight": 180,
     "price": 150,
     "imgSrc": "california-tempura.jpg"
 }   
]